pyreadsb/__init__.py
pyreadsb/compression_utils.py
pyreadsb/heatmap_decoder.py
pyreadsb/heatmap_to_dataframe.py
pyreadsb/py.typed
pyreadsb/traces_decoder.py
pyreadsb/traces_to_dataframe.py
pyreadsb-1.3.2.dist-info/METADATA
pyreadsb-1.3.2.dist-info/WHEEL
pyreadsb-1.3.2.dist-info/licenses/LICENSE
pyreadsb-1.3.2.dist-info/RECORD
